mabby/__init__.py
mabby/agent.py
mabby/arms.py
mabby/bandit.py
mabby/exceptions.py
mabby/simulation.py
mabby/stats.py
mabby/strategies/__init__.py
mabby/strategies/semi_uniform.py
mabby/strategies/strategy.py
mabby/strategies/thompson.py
mabby/strategies/ucb.py
mabby/utils.py
mabby-0.1.2.dist-info/LICENSE
mabby-0.1.2.dist-info/WHEEL
mabby-0.1.2.dist-info/METADATA
mabby-0.1.2.dist-info/RECORD
