Metadata-Version: 2.1
Name: mabby
Version: 0.1.2
Summary: A multi-armed bandit (MAB) simulation library
License: Apache-2.0
Author: Ethan Wu
Author-email: ew2664@columbia.edu
Requires-Python: >=3.9,<4.0
Classifier: License :: OSI Approved :: Apache Software License
Classifier: Programming Language :: Python :: 3
Classifier: Programming Language :: Python :: 3.9
Classifier: Programming Language :: Python :: 3.10
Classifier: Programming Language :: Python :: 3.11
Requires-Dist: matplotlib (>=3.7.0,<4.0.0)
Requires-Dist: numpy (>=1.24.2,<2.0.0)
Requires-Dist: overrides (>=7.3.1,<8.0.0)
